{
  "host": "localhost",
  "port": 3030,
  "public": "../public/",
  "paginate": {
    "default": 10,
    "max": 50
  },
  "authentication": {
    "secret": "your-secret-key",
    "strategies": [
      "jwt",
      "local"
    ],
    "jwt": {
      "header": {
        "type": "access"
      },
      "audience": "https://yourdomain.com",
      "subject": "anonymous",
      "issuer": "feathers",
      "algorithm": "HS256",
      "expiresIn": "1d"
    },
    "local": {
      "entity": "users",
      "usernameField": "email",
      "passwordField": "password"
    }
  },
  "postgres": "postgresql://MasonHirst:v2_3zgua_vc6GgW6gf7RZNKQMA3bc8Nm@db.bit.io:5432/MasonHirst/Kmail"
}
